openetran_py3/Add_Delete_Widgets.py
openetran_py3/CSVRead.py
openetran_py3/Draw.py
openetran_py3/GUI.py
openetran_py3/ParseInput.py
openetran_py3/Plot2D.py
openetran_py3/Project.py
openetran_py3/R60.py
openetran_py3/ReadStruct.py
openetran_py3/WriteGUI.py
openetran_py3/__init__.py
openetran_py3/docs/Documentation.txt
openetran_py3/win/CFO_Added.xlsm
openetran_py3/win/libgsl-19.dll
openetran_py3/win/libgslcblas-0.dll
openetran_py3/win/openetran.exe
openetran_py3-1.0.0.data/scripts/postinst.py
openetran_py3-1.0.0.dist-info/DESCRIPTION.rst
openetran_py3-1.0.0.dist-info/METADATA
openetran_py3-1.0.0.dist-info/RECORD
openetran_py3-1.0.0.dist-info/WHEEL
openetran_py3-1.0.0.dist-info/entry_points.txt
openetran_py3-1.0.0.dist-info/metadata.json
openetran_py3-1.0.0.dist-info/top_level.txt
