Metadata-Version: 2.0
Name: openetran-py3
Version: 1.0.0
Summary: OpenEtran executable and GUI
Home-page: https://github.com/MAB522/OpenETran
Author: Matthieu Bertin
Author-email: MAB522@pitt.edu
License: GPL v3 License
Platform: UNKNOWN
Requires-Dist: PyQt5 (>=5.6)
Requires-Dist: matplotlib (==2.0.2)
